drf_proxy_pagination-0.2.0.dist-info/DESCRIPTION.rst
drf_proxy_pagination-0.2.0.dist-info/METADATA
drf_proxy_pagination-0.2.0.dist-info/metadata.json
drf_proxy_pagination-0.2.0.dist-info/RECORD
drf_proxy_pagination-0.2.0.dist-info/top_level.txt
drf_proxy_pagination-0.2.0.dist-info/WHEEL
proxy_pagination/__init__.py
